Reddithor/__init__.py
Reddithor/appindicator_replacement.py
Reddithor/custom_dialog.py
Reddithor/reddithor_fetch.py
Reddithor/version.py
Reddithor/data/__init__.py
Reddithor/data/snoo.png
Reddithor-0.0.5.dist-info/DESCRIPTION.rst
Reddithor-0.0.5.dist-info/METADATA
Reddithor-0.0.5.dist-info/RECORD
Reddithor-0.0.5.dist-info/WHEEL
Reddithor-0.0.5.dist-info/entry_points.txt
Reddithor-0.0.5.dist-info/metadata.json
Reddithor-0.0.5.dist-info/top_level.txt
