Metadata-Version: 2.0
Name: Reddithor
Version: 0.0.5
Summary: Stay updated with a subreddit of your choice.
Home-page: https://github.com/Murtaza0xFF/Reddithor
Author: Murtaza Akbari
Author-email: murtazasakbari@gmail.com
License: Apache License, Version 2.0
Keywords: reddit Reddithor subreddit Linux
Platform: UNKNOWN
Classifier: Development Status :: 4 - Beta
Requires-Dist: requests (>=2.2.1)
